packme/PackerTemplate.py
packme/Packman.py
packme/__init__.py
packme/__pkginfo__.py
packme-0.8.0.data/data/stubs/packme/PackerTemplate.pyi
packme-0.8.0.data/data/stubs/packme/Packman.pyi
packme-0.8.0.data/data/stubs/packme/__init__.pyi
packme-0.8.0.data/data/stubs/packme/__pkginfo__.pyi
packme-0.8.0.data/scripts/packme
packme-0.8.0.dist-info/COPYING
packme-0.8.0.dist-info/LICENSE
packme-0.8.0.dist-info/METADATA
packme-0.8.0.dist-info/WHEEL
packme-0.8.0.dist-info/top_level.txt
packme-0.8.0.dist-info/RECORD
