Metadata-Version: 2.1
Name: packme
Version: 0.8.0
Summary: Helper app for building and running packer templates
Home-page: https://code.ill.fr/panosc/data-analysis-services/packme
Author: Eric Pellegrini
Author-email: pellegrini@ill.fr
Maintainer: Eric Pellegrini
Maintainer-email: pellegrini@ill.fr
License: MIT
Platform: Unix
Platform: Windows
Classifier: Programming Language :: Python :: 3
Classifier: License :: OSI Approved :: MIT License
Classifier: Intended Audience :: Developers
Classifier: Operating System :: POSIX :: Linux
Classifier: Natural Language :: English
Classifier: Environment :: Console
Classifier: Topic :: Software Development :: Libraries :: Python Modules
Classifier: Topic :: System :: Installation/Setup
Classifier: Topic :: System :: Operating System Kernels :: Linux
Requires-Dist: jinja2
Requires-Dist: pyyaml
